Metadata-Version: 2.1
Name: speechToTextPy
Version: 0.0.2
Summary: SpeechRecognition and Translation.
Author-email: ranjitmaity95@gmail.com
